{"lea_id": "320", "lea_nces_id": "4700001", "nces_id": "470000101930", "id": "14", "name": "John Hay Elementary", "type": 1, "url": "www.hcboe.net/Main/School/JH/JHHomePage", "phone": "4235861080", "mailing_address": {"street_address": "501  Brittain  Court ", "extended_address": "", "locality": "Morristown", "region": "TN", "postal_code": "37814"}, "physical_address": {"street_address": "501  Brittain  Court ", "extended_address": "", "locality": "Morristown", "region": "TN", "postal_code": "37814"}, "is_charter": false, "grades_served": ["K", "5"], "safe_school": true, "membership": {"average_daily": 259, "total": 260, "white": {"total": 159, "male": 69, "female": 74}, "african_american": {"total": 17, "male": null, "female": null}, "hispancic": {"total": 81, "male": 29, "female": 18}, "asian": {"total": null, "male": null, "female": null}, "native_american": {"total": null, "male": null, "female": null}, "limited_english_proficient": 64, "exempt_from_reading_assessment": null, "students_with_disabilities": 20, "free_lunch_eligible": 169, "reduced_lunch_eligible": 18, "free_reduced_lunch_eligible": 187, "title_i": 259}, "accountability": {"math": {"all": {"all": {"valid_tests": 130, "below_basic_percentage": 2.3, "below_basic": 3.0, "basic_percentage": 20.0, "basic": 26.0, "proficient_percentage": 46.9, "proficient": 61.0, "advanced_percentage": 30.8, "percentage": 40.0}, "white": {"valid_tests": 87, "below_basic_percentage": 1.2, "below_basic": 1.0, "basic_percentage": 18.4, "basic": 16.0, "proficient_percentage": 47.1, "proficient": 41.0, "advanced_percentage": 33.3, "percentage": 29.0}, "hispanic": {"valid_tests": 35, "below_basic_percentage": 5.7, "below_basic": 2.0, "basic_percentage": 22.9, "basic": 8.0, "proficient_percentage": 45.7, "proficient": 16.0, "advanced_percentage": 25.7, "percentage": 9.0}, "black": {"valid_tests": null, "below_basic_percentage": null, "below_basic": null, "basic_percentage": null, "basic": null, "proficient_percentage": null, "proficient": null, "advanced_percentage": null, "percentage": null}, "asian": {"valid_tests": null, "below_basic_percentage": null, "below_basic": null, "basic_percentage": null, "basic": null, "proficient_percentage": null, "proficient": null, "advanced_percentage": null, "percentage": null}, "native_american": {"valid_tests": null, "below_basic_percentage": null, "below_basic": null, "basic_percentage": null, "basic": null, "proficient_percentage": null, "proficient": null, "advanced_percentage": null, "percentage": null}, "hawaiian_or_pacific_islander": {"valid_tests": null, "below_basic_percentage": null, "below_basic": null, "basic_percentage": null, "basic": null, "proficient_percentage": null, "proficient": null, "advanced_percentage": null, "percentage": null}, "economically_disadvantaged": {"valid_tests": 89, "below_basic_percentage": 3.4, "below_basic": 3.0, "basic_percentage": 22.5, "basic": 20.0, "proficient_percentage": 49.4, "proficient": 44.0, "advanced_percentage": 24.7, "percentage": 22.0}, "students_with_disabilities": {"valid_tests": 12, "below_basic_percentage": 0.0, "below_basic": 0.0, "basic_percentage": 33.3, "basic": 4.0, "proficient_percentage": 41.7, "proficient": 5.0, "advanced_percentage": 25.0, "percentage": 3.0}, "english_language_learners": {"valid_tests": 13, "below_basic_percentage": 15.3, "below_basic": 2.0, "basic_percentage": 46.2, "basic": 6.0, "proficient_percentage": 38.5, "proficient": 5.0, "advanced_percentage": 0.0, "percentage": 0.0}, "english_language_learners_with_t1_t2": {"valid_tests": 24, "below_basic_percentage": 8.4, "below_basic": 2.0, "basic_percentage": 33.3, "basic": 8.0, "proficient_percentage": 45.8, "proficient": 11.0, "advanced_percentage": 12.5, "percentage": 3.0}, "black_hispanic_native_american": {"valid_tests": 41, "below_basic_percentage": 4.8, "below_basic": 2.0, "basic_percentage": 22.0, "basic": 9.0, "proficient_percentage": 48.8, "proficient": 20.0, "advanced_percentage": 24.4, "percentage": 10.0}}, "3": {"all": {"valid_tests": 49, "below_basic_percentage": 0.0, "below_basic": 0.0, "basic_percentage": 10.2, "basic": 5.0, "proficient_percentage": 53.1, "proficient": 26.0, "advanced_percentage": 36.7, "percentage": 18.0}, "white": {"valid_tests": 36, "below_basic_percentage": 0.1, "below_basic": 0.0, "basic_percentage": 8.3, "basic": 3.0, "proficient_percentage": 47.2, "proficient": 17.0, "advanced_percentage": 44.4, "percentage": 16.0}, "hispanic": {"valid_tests": 11, "below_basic_percentage": 0.0, "below_basic": 0.0, "basic_percentage": 9.1, "basic": 1.0, "proficient_percentage": 72.7, "proficient": 8.0, "advanced_percentage": 18.2, "percentage": 2.0}, "black": {"valid_tests": null, "below_basic_percentage": null, "below_basic": null, "basic_percentage": null, "basic": null, "proficient_percentage": null, "proficient": null, "advanced_percentage": null, "percentage": null}, "asian": {"valid_tests": null, "below_basic_percentage": null, "below_basic": null, "basic_percentage": null, "basic": null, "proficient_percentage": null, "proficient": null, "advanced_percentage": null, "percentage": null}, "native_american": {"valid_tests": null, "below_basic_percentage": null, "below_basic": null, "basic_percentage": null, "basic": null, "proficient_percentage": null, "proficient": null, "advanced_percentage": null, "percentage": null}, "hawaiian_or_pacific_islander": {"valid_tests": null, "below_basic_percentage": null, "below_basic": null, "basic_percentage": null, "basic": null, "proficient_percentage": null, "proficient": null, "advanced_percentage": null, "percentage": null}, "economically_disadvantaged": {"valid_tests": 27, "below_basic_percentage": 0.0, "below_basic": 0.0, "basic_percentage": 11.1, "basic": 3.0, "proficient_percentage": 63.0, "proficient": 17.0, "advanced_percentage": 25.9, "percentage": 7.0}, "students_with_disabilities": {"valid_tests": null, "below_basic_percentage": null, "below_basic": null, "basic_percentage": null, "basic": null, "proficient_percentage": null, "proficient": null, "advanced_percentage": null, "percentage": null}, "english_language_learners": {"valid_tests": null, "below_basic_percentage": null, "below_basic": null, "basic_percentage": null, "basic": null, "proficient_percentage": null, "proficient": null, "advanced_percentage": null, "percentage": null}, "english_language_learners_with_t1_t2": {"valid_tests": null, "below_basic_percentage": null, "below_basic": null, "basic_percentage": null, "basic": null, "proficient_percentage": null, "proficient": null, "advanced_percentage": null, "percentage": null}, "black_hispanic_native_american": {"valid_tests": 13, "below_basic_percentage": 0.0, "below_basic": 0.0, "basic_percentage": 15.4, "basic": 2.0, "proficient_percentage": 69.2, "proficient": 9.0, "advanced_percentage": 15.4, "percentage": 2.0}}, "4": {"all": {"valid_tests": 43, "below_basic_percentage": 7.0, "below_basic": 3.0, "basic_percentage": 34.9, "basic": 15.0, "proficient_percentage": 37.2, "proficient": 16.0, "advanced_percentage": 20.9, "percentage": 9.0}, "white": {"valid_tests": 27, "below_basic_percentage": 3.8, "below_basic": 1.0, "basic_percentage": 33.3, "basic": 9.0, "proficient_percentage": 44.4, "proficient": 12.0, "advanced_percentage": 18.5, "percentage": 5.0}, "hispanic": {"valid_tests": 12, "below_basic_percentage": 16.6, "below_basic": 2.0, "basic_percentage": 50.0, "basic": 6.0, "proficient_percentage": 16.7, "proficient": 2.0, "advanced_percentage": 16.7, "percentage": 2.0}, "black": {"valid_tests": null, "below_basic_percentage": null, "below_basic": null, "basic_percentage": null, "basic": null, "proficient_percentage": null, "proficient": null, "advanced_percentage": null, "percentage": null}, "asian": {"valid_tests": null, "below_basic_percentage": null, "below_basic": null, "basic_percentage": null, "basic": null, "proficient_percentage": null, "proficient": null, "advanced_percentage": null, "percentage": null}, "native_american": {"valid_tests": null, "below_basic_percentage": null, "below_basic": null, "basic_percentage": null, "basic": null, "proficient_percentage": null, "proficient": null, "advanced_percentage": null, "percentage": null}, "hawaiian_or_pacific_islander": {"valid_tests": null, "below_basic_percentage": null, "below_basic": null, "basic_percentage": null, "basic": null, "proficient_percentage": null, "proficient": null, "advanced_percentage": null, "percentage": null}, "economically_disadvantaged": {"valid_tests": 33, "below_basic_percentage": 9.0, "below_basic": 3.0, "basic_percentage": 36.4, "basic": 12.0, "proficient_percentage": 39.4, "proficient": 13.0, "advanced_percentage": 15.2, "percentage": 5.0}, "students_with_disabilities": {"valid_tests": null, "below_basic_percentage": null, "below_basic": null, "basic_percentage": null, "basic": null, "proficient_percentage": null, "proficient": null, "advanced_percentage": null, "percentage": null}, "english_language_learners": {"valid_tests": null, "below_basic_percentage": null, "below_basic": null, "basic_percentage": null, "basic": null, "proficient_percentage": null, "proficient": null, "advanced_percentage": null, "percentage": null}, "english_language_learners_with_t1_t2": {"valid_tests": 10, "below_basic_percentage": 20.0, "below_basic": 2.0, "basic_percentage": 60.0, "basic": 6.0, "proficient_percentage": 20.0, "proficient": 2.0, "advanced_percentage": 0.0, "percentage": 0.0}, "black_hispanic_native_american": {"valid_tests": 15, "below_basic_percentage": 13.3, "below_basic": 2.0, "basic_percentage": 40.0, "basic": 6.0, "proficient_percentage": 26.7, "proficient": 4.0, "advanced_percentage": 20.0, "percentage": 3.0}}, "5": {"all": {"valid_tests": 38, "below_basic_percentage": 0.0, "below_basic": 0.0, "basic_percentage": 15.8, "basic": 6.0, "proficient_percentage": 50.0, "proficient": 19.0, "advanced_percentage": 34.2, "percentage": 13.0}, "white": {"valid_tests": 24, "below_basic_percentage": 0.0, "below_basic": 0.0, "basic_percentage": 16.7, "basic": 4.0, "proficient_percentage": 50.0, "proficient": 12.0, "advanced_percentage": 33.3, "percentage": 8.0}, "hispanic": {"valid_tests": 12, "below_basic_percentage": 0.0, "below_basic": 0.0, "basic_percentage": 8.3, "basic": 1.0, "proficient_percentage": 50.0, "proficient": 6.0, "advanced_percentage": 41.7, "percentage": 5.0}, "black": {"valid_tests": null, "below_basic_percentage": null, "below_basic": null, "basic_percentage": null, "basic": null, "proficient_percentage": null, "proficient": null, "advanced_percentage": null, "percentage": null}, "asian": {"valid_tests": null, "below_basic_percentage": null, "below_basic": null, "basic_percentage": null, "basic": null, "proficient_percentage": null, "proficient": null, "advanced_percentage": null, "percentage": null}, "native_american": {"valid_tests": null, "below_basic_percentage": null, "below_basic": null, "basic_percentage": null, "basic": null, "proficient_percentage": null, "proficient": null, "advanced_percentage": null, "percentage": null}, "hawaiian_or_pacific_islander": {"valid_tests": null, "below_basic_percentage": null, "below_basic": null, "basic_percentage": null, "basic": null, "proficient_percentage": null, "proficient": null, "advanced_percentage": null, "percentage": null}, "economically_disadvantaged": {"valid_tests": 29, "below_basic_percentage": 0.0, "below_basic": 0.0, "basic_percentage": 17.2, "basic": 5.0, "proficient_percentage": 48.3, "proficient": 14.0, "advanced_percentage": 34.5, "percentage": 10.0}, "students_with_disabilities": {"valid_tests": null, "below_basic_percentage": null, "below_basic": null, "basic_percentage": null, "basic": null, "proficient_percentage": null, "proficient": null, "advanced_percentage": null, "percentage": null}, "english_language_learners": {"valid_tests": null, "below_basic_percentage": null, "below_basic": null, "basic_percentage": null, "basic": null, "proficient_percentage": null, "proficient": null, "advanced_percentage": null, "percentage": null}, "english_language_learners_with_t1_t2": {"valid_tests": null, "below_basic_percentage": null, "below_basic": null, "basic_percentage": null, "basic": null, "proficient_percentage": null, "proficient": null, "advanced_percentage": null, "percentage": null}, "black_hispanic_native_american": {"valid_tests": 13, "below_basic_percentage": 0.0, "below_basic": 0.0, "basic_percentage": 7.7, "basic": 1.0, "proficient_percentage": 53.8, "proficient": 7.0, "advanced_percentage": 38.5, "percentage": 5.0}}}, "rla": {"all": {"all": {"valid_tests": 130, "below_basic_percentage": 3.8, "below_basic": 5.0, "basic_percentage": 36.9, "basic": 48.0, "proficient_percentage": 50.8, "proficient": 66.0, "advanced_percentage": 8.5, "percentage": 11.0}, "white": {"valid_tests": 87, "below_basic_percentage": 1.2, "below_basic": 1.0, "basic_percentage": 35.6, "basic": 31.0, "proficient_percentage": 54.0, "proficient": 47.0, "advanced_percentage": 9.2, "percentage": 8.0}, "hispanic": {"valid_tests": 35, "below_basic_percentage": 8.5, "below_basic": 3.0, "basic_percentage": 42.9, "basic": 15.0, "proficient_percentage": 42.9, "proficient": 15.0, "advanced_percentage": 5.7, "percentage": 2.0}, "black": {"valid_tests": null, "below_basic_percentage": null, "below_basic": null, "basic_percentage": null, "basic": null, "proficient_percentage": null, "proficient": null, "advanced_percentage": null, "percentage": null}, "asian": {"valid_tests": null, "below_basic_percentage": null, "below_basic": null, "basic_percentage": null, "basic": null, "proficient_percentage": null, "proficient": null, "advanced_percentage": null, "percentage": null}, "native_american": {"valid_tests": null, "below_basic_percentage": null, "below_basic": null, "basic_percentage": null, "basic": null, "proficient_percentage": null, "proficient": null, "advanced_percentage": null, "percentage": null}, "hawaiian_or_pacific_islander": {"valid_tests": null, "below_basic_percentage": null, "below_basic": null, "basic_percentage": null, "basic": null, "proficient_percentage": null, "proficient": null, "advanced_percentage": null, "percentage": null}, "economically_disadvantaged": {"valid_tests": 89, "below_basic_percentage": 5.7, "below_basic": 5.0, "basic_percentage": 43.8, "basic": 39.0, "proficient_percentage": 43.8, "proficient": 39.0, "advanced_percentage": 6.7, "percentage": 6.0}, "students_with_disabilities": {"valid_tests": 12, "below_basic_percentage": 8.3, "below_basic": 1.0, "basic_percentage": 33.3, "basic": 4.0, "proficient_percentage": 41.7, "proficient": 5.0, "advanced_percentage": 16.7, "percentage": 2.0}, "english_language_learners": {"valid_tests": 13, "below_basic_percentage": 30.8, "below_basic": 4.0, "basic_percentage": 61.5, "basic": 8.0, "proficient_percentage": 7.7, "proficient": 1.0, "advanced_percentage": 0.0, "percentage": 0.0}, "english_language_learners_with_t1_t2": {"valid_tests": 24, "below_basic_percentage": 16.7, "below_basic": 4.0, "basic_percentage": 58.3, "basic": 14.0, "proficient_percentage": 20.8, "proficient": 5.0, "advanced_percentage": 4.2, "percentage": 1.0}, "black_hispanic_native_american": {"valid_tests": 41, "below_basic_percentage": 7.3, "below_basic": 3.0, "basic_percentage": 41.5, "basic": 17.0, "proficient_percentage": 43.9, "proficient": 18.0, "advanced_percentage": 7.3, "percentage": 3.0}}, "3": {"all": {"valid_tests": 49, "below_basic_percentage": 2.0, "below_basic": 1.0, "basic_percentage": 28.6, "basic": 14.0, "proficient_percentage": 59.2, "proficient": 29.0, "advanced_percentage": 10.2, "percentage": 5.0}, "white": {"valid_tests": 36, "below_basic_percentage": 0.0, "below_basic": 0.0, "basic_percentage": 19.4, "basic": 7.0, "proficient_percentage": 66.7, "proficient": 24.0, "advanced_percentage": 13.9, "percentage": 5.0}, "hispanic": {"valid_tests": 11, "below_basic_percentage": 9.0, "below_basic": 1.0, "basic_percentage": 45.5, "basic": 5.0, "proficient_percentage": 45.5, "proficient": 5.0, "advanced_percentage": 0.0, "percentage": 0.0}, "black": {"valid_tests": null, "below_basic_percentage": null, "below_basic": null, "basic_percentage": null, "basic": null, "proficient_percentage": null, "proficient": null, "advanced_percentage": null, "percentage": null}, "asian": {"valid_tests": null, "below_basic_percentage": null, "below_basic": null, "basic_percentage": null, "basic": null, "proficient_percentage": null, "proficient": null, "advanced_percentage": null, "percentage": null}, "native_american": {"valid_tests": null, "below_basic_percentage": null, "below_basic": null, "basic_percentage": null, "basic": null, "proficient_percentage": null, "proficient": null, "advanced_percentage": null, "percentage": null}, "hawaiian_or_pacific_islander": {"valid_tests": null, "below_basic_percentage": null, "below_basic": null, "basic_percentage": null, "basic": null, "proficient_percentage": null, "proficient": null, "advanced_percentage": null, "percentage": null}, "economically_disadvantaged": {"valid_tests": 27, "below_basic_percentage": 3.7, "below_basic": 1.0, "basic_percentage": 37.0, "basic": 10.0, "proficient_percentage": 51.9, "proficient": 14.0, "advanced_percentage": 7.4, "percentage": 2.0}, "students_with_disabilities": {"valid_tests": null, "below_basic_percentage": null, "below_basic": null, "basic_percentage": null, "basic": null, "proficient_percentage": null, "proficient": null, "advanced_percentage": null, "percentage": null}, "english_language_learners": {"valid_tests": null, "below_basic_percentage": null, "below_basic": null, "basic_percentage": null, "basic": null, "proficient_percentage": null, "proficient": null, "advanced_percentage": null, "percentage": null}, "english_language_learners_with_t1_t2": {"valid_tests": null, "below_basic_percentage": null, "below_basic": null, "basic_percentage": null, "basic": null, "proficient_percentage": null, "proficient": null, "advanced_percentage": null, "percentage": null}, "black_hispanic_native_american": {"valid_tests": 13, "below_basic_percentage": 7.7, "below_basic": 1.0, "basic_percentage": 53.8, "basic": 7.0, "proficient_percentage": 38.5, "proficient": 5.0, "advanced_percentage": 0.0, "percentage": 0.0}}, "4": {"all": {"valid_tests": 43, "below_basic_percentage": 7.0, "below_basic": 3.0, "basic_percentage": 48.8, "basic": 21.0, "proficient_percentage": 37.2, "proficient": 16.0, "advanced_percentage": 7.0, "percentage": 3.0}, "white": {"valid_tests": 27, "below_basic_percentage": 3.7, "below_basic": 1.0, "basic_percentage": 51.9, "basic": 14.0, "proficient_percentage": 37.0, "proficient": 10.0, "advanced_percentage": 7.4, "percentage": 2.0}, "hispanic": {"valid_tests": 12, "below_basic_percentage": 16.7, "below_basic": 2.0, "basic_percentage": 58.3, "basic": 7.0, "proficient_percentage": 25.0, "proficient": 3.0, "advanced_percentage": 0.0, "percentage": 0.0}, "black": {"valid_tests": null, "below_basic_percentage": null, "below_basic": null, "basic_percentage": null, "basic": null, "proficient_percentage": null, "proficient": null, "advanced_percentage": null, "percentage": null}, "asian": {"valid_tests": null, "below_basic_percentage": null, "below_basic": null, "basic_percentage": null, "basic": null, "proficient_percentage": null, "proficient": null, "advanced_percentage": null, "percentage": null}, "native_american": {"valid_tests": null, "below_basic_percentage": null, "below_basic": null, "basic_percentage": null, "basic": null, "proficient_percentage": null, "proficient": null, "advanced_percentage": null, "percentage": null}, "hawaiian_or_pacific_islander": {"valid_tests": null, "below_basic_percentage": null, "below_basic": null, "basic_percentage": null, "basic": null, "proficient_percentage": null, "proficient": null, "advanced_percentage": null, "percentage": null}, "economically_disadvantaged": {"valid_tests": 33, "below_basic_percentage": 9.1, "below_basic": 3.0, "basic_percentage": 57.6, "basic": 19.0, "proficient_percentage": 30.3, "proficient": 10.0, "advanced_percentage": 3.0, "percentage": 1.0}, "students_with_disabilities": {"valid_tests": null, "below_basic_percentage": null, "below_basic": null, "basic_percentage": null, "basic": null, "proficient_percentage": null, "proficient": null, "advanced_percentage": null, "percentage": null}, "english_language_learners": {"valid_tests": null, "below_basic_percentage": null, "below_basic": null, "basic_percentage": null, "basic": null, "proficient_percentage": null, "proficient": null, "advanced_percentage": null, "percentage": null}, "english_language_learners_with_t1_t2": {"valid_tests": 10, "below_basic_percentage": 20.0, "below_basic": 2.0, "basic_percentage": 70.0, "basic": 7.0, "proficient_percentage": 10.0, "proficient": 1.0, "advanced_percentage": 0.0, "percentage": 0.0}, "black_hispanic_native_american": {"valid_tests": 15, "below_basic_percentage": 13.3, "below_basic": 2.0, "basic_percentage": 46.7, "basic": 7.0, "proficient_percentage": 33.3, "proficient": 5.0, "advanced_percentage": 6.7, "percentage": 1.0}}, "5": {"all": {"valid_tests": 38, "below_basic_percentage": 2.6, "below_basic": 1.0, "basic_percentage": 34.2, "basic": 13.0, "proficient_percentage": 55.3, "proficient": 21.0, "advanced_percentage": 7.9, "percentage": 3.0}, "white": {"valid_tests": 24, "below_basic_percentage": 0.0, "below_basic": 0.0, "basic_percentage": 41.6, "basic": 10.0, "proficient_percentage": 54.2, "proficient": 13.0, "advanced_percentage": 4.2, "percentage": 1.0}, "hispanic": {"valid_tests": 12, "below_basic_percentage": 0.0, "below_basic": 0.0, "basic_percentage": 25.0, "basic": 3.0, "proficient_percentage": 58.3, "proficient": 7.0, "advanced_percentage": 16.7, "percentage": 2.0}, "black": {"valid_tests": null, "below_basic_percentage": null, "below_basic": null, "basic_percentage": null, "basic": null, "proficient_percentage": null, "proficient": null, "advanced_percentage": null, "percentage": null}, "asian": {"valid_tests": null, "below_basic_percentage": null, "below_basic": null, "basic_percentage": null, "basic": null, "proficient_percentage": null, "proficient": null, "advanced_percentage": null, "percentage": null}, "native_american": {"valid_tests": null, "below_basic_percentage": null, "below_basic": null, "basic_percentage": null, "basic": null, "proficient_percentage": null, "proficient": null, "advanced_percentage": null, "percentage": null}, "hawaiian_or_pacific_islander": {"valid_tests": null, "below_basic_percentage": null, "below_basic": null, "basic_percentage": null, "basic": null, "proficient_percentage": null, "proficient": null, "advanced_percentage": null, "percentage": null}, "economically_disadvantaged": {"valid_tests": 29, "below_basic_percentage": 3.5, "below_basic": 1.0, "basic_percentage": 34.5, "basic": 10.0, "proficient_percentage": 51.7, "proficient": 15.0, "advanced_percentage": 10.3, "percentage": 3.0}, "students_with_disabilities": {"valid_tests": null, "below_basic_percentage": null, "below_basic": null, "basic_percentage": null, "basic": null, "proficient_percentage": null, "proficient": null, "advanced_percentage": null, "percentage": null}, "english_language_learners": {"valid_tests": null, "below_basic_percentage": null, "below_basic": null, "basic_percentage": null, "basic": null, "proficient_percentage": null, "proficient": null, "advanced_percentage": null, "percentage": null}, "english_language_learners_with_t1_t2": {"valid_tests": null, "below_basic_percentage": null, "below_basic": null, "basic_percentage": null, "basic": null, "proficient_percentage": null, "proficient": null, "advanced_percentage": null, "percentage": null}, "black_hispanic_native_american": {"valid_tests": 13, "below_basic_percentage": 0.0, "below_basic": 0.0, "basic_percentage": 23.1, "basic": 3.0, "proficient_percentage": 61.5, "proficient": 8.0, "advanced_percentage": 15.4, "percentage": 2.0}}}, "science": {"all": {"all": {"valid_tests": 130, "below_basic_percentage": 7.7, "below_basic": 10.0, "basic_percentage": 15.4, "basic": 20.0, "proficient_percentage": 56.9, "proficient": 74.0, "advanced_percentage": 20.0, "percentage": 26.0}, "white": {"valid_tests": 87, "below_basic_percentage": 3.5, "below_basic": 3.0, "basic_percentage": 12.6, "basic": 11.0, "proficient_percentage": 60.9, "proficient": 53.0, "advanced_percentage": 23.0, "percentage": 20.0}, "hispanic": {"valid_tests": 35, "below_basic_percentage": 17.1, "below_basic": 6.0, "basic_percentage": 22.9, "basic": 8.0, "proficient_percentage": 48.6, "proficient": 17.0, "advanced_percentage": 11.4, "percentage": 4.0}, "black": {"valid_tests": null, "below_basic_percentage": null, "below_basic": null, "basic_percentage": null, "basic": null, "proficient_percentage": null, "proficient": null, "advanced_percentage": null, "percentage": null}, "asian": {"valid_tests": null, "below_basic_percentage": null, "below_basic": null, "basic_percentage": null, "basic": null, "proficient_percentage": null, "proficient": null, "advanced_percentage": null, "percentage": null}, "native_american": {"valid_tests": null, "below_basic_percentage": null, "below_basic": null, "basic_percentage": null, "basic": null, "proficient_percentage": null, "proficient": null, "advanced_percentage": null, "percentage": null}, "hawaiian_or_pacific_islander": {"valid_tests": null, "below_basic_percentage": null, "below_basic": null, "basic_percentage": null, "basic": null, "proficient_percentage": null, "proficient": null, "advanced_percentage": null, "percentage": null}, "economically_disadvantaged": {"valid_tests": 89, "below_basic_percentage": 8.9, "below_basic": 8.0, "basic_percentage": 18.0, "basic": 16.0, "proficient_percentage": 60.7, "proficient": 54.0, "advanced_percentage": 12.4, "percentage": 11.0}, "students_with_disabilities": {"valid_tests": 12, "below_basic_percentage": 8.4, "below_basic": 1.0, "basic_percentage": 33.3, "basic": 4.0, "proficient_percentage": 25.0, "proficient": 3.0, "advanced_percentage": 33.3, "percentage": 4.0}, "english_language_learners": {"valid_tests": 13, "below_basic_percentage": 46.1, "below_basic": 6.0, "basic_percentage": 23.1, "basic": 3.0, "proficient_percentage": 23.1, "proficient": 3.0, "advanced_percentage": 7.7, "percentage": 1.0}, "english_language_learners_with_t1_t2": {"valid_tests": 24, "below_basic_percentage": 25.0, "below_basic": 6.0, "basic_percentage": 25.0, "basic": 6.0, "proficient_percentage": 37.5, "proficient": 9.0, "advanced_percentage": 12.5, "percentage": 3.0}, "black_hispanic_native_american": {"valid_tests": 41, "below_basic_percentage": 14.6, "below_basic": 6.0, "basic_percentage": 22.0, "basic": 9.0, "proficient_percentage": 51.2, "proficient": 21.0, "advanced_percentage": 12.2, "percentage": 5.0}}, "3": {"all": {"valid_tests": 49, "below_basic_percentage": 4.1, "below_basic": 2.0, "basic_percentage": 10.2, "basic": 5.0, "proficient_percentage": 63.3, "proficient": 31.0, "advanced_percentage": 22.4, "percentage": 11.0}, "white": {"valid_tests": 36, "below_basic_percentage": 0.0, "below_basic": 0.0, "basic_percentage": 5.5, "basic": 2.0, "proficient_percentage": 63.9, "proficient": 23.0, "advanced_percentage": 30.6, "percentage": 11.0}, "hispanic": {"valid_tests": 11, "below_basic_percentage": 18.2, "below_basic": 2.0, "basic_percentage": 18.2, "basic": 2.0, "proficient_percentage": 63.6, "proficient": 7.0, "advanced_percentage": 0.0, "percentage": 0.0}, "black": {"valid_tests": null, "below_basic_percentage": null, "below_basic": null, "basic_percentage": null, "basic": null, "proficient_percentage": null, "proficient": null, "advanced_percentage": null, "percentage": null}, "asian": {"valid_tests": null, "below_basic_percentage": null, "below_basic": null, "basic_percentage": null, "basic": null, "proficient_percentage": null, "proficient": null, "advanced_percentage": null, "percentage": null}, "native_american": {"valid_tests": null, "below_basic_percentage": null, "below_basic": null, "basic_percentage": null, "basic": null, "proficient_percentage": null, "proficient": null, "advanced_percentage": null, "percentage": null}, "hawaiian_or_pacific_islander": {"valid_tests": null, "below_basic_percentage": null, "below_basic": null, "basic_percentage": null, "basic": null, "proficient_percentage": null, "proficient": null, "advanced_percentage": null, "percentage": null}, "economically_disadvantaged": {"valid_tests": 27, "below_basic_percentage": 7.4, "below_basic": 2.0, "basic_percentage": 7.4, "basic": 2.0, "proficient_percentage": 74.1, "proficient": 20.0, "advanced_percentage": 11.1, "percentage": 3.0}, "students_with_disabilities": {"valid_tests": null, "below_basic_percentage": null, "below_basic": null, "basic_percentage": null, "basic": null, "proficient_percentage": null, "proficient": null, "advanced_percentage": null, "percentage": null}, "english_language_learners": {"valid_tests": null, "below_basic_percentage": null, "below_basic": null, "basic_percentage": null, "basic": null, "proficient_percentage": null, "proficient": null, "advanced_percentage": null, "percentage": null}, "english_language_learners_with_t1_t2": {"valid_tests": null, "below_basic_percentage": null, "below_basic": null, "basic_percentage": null, "basic": null, "proficient_percentage": null, "proficient": null, "advanced_percentage": null, "percentage": null}, "black_hispanic_native_american": {"valid_tests": 13, "below_basic_percentage": 15.4, "below_basic": 2.0, "basic_percentage": 23.1, "basic": 3.0, "proficient_percentage": 61.5, "proficient": 8.0, "advanced_percentage": 0.0, "percentage": 0.0}}, "4": {"all": {"valid_tests": 43, "below_basic_percentage": 4.6, "below_basic": 2.0, "basic_percentage": 20.9, "basic": 9.0, "proficient_percentage": 51.2, "proficient": 22.0, "advanced_percentage": 23.3, "percentage": 10.0}, "white": {"valid_tests": 27, "below_basic_percentage": 0.0, "below_basic": 0.0, "basic_percentage": 18.5, "basic": 5.0, "proficient_percentage": 63.0, "proficient": 17.0, "advanced_percentage": 18.5, "percentage": 5.0}, "hispanic": {"valid_tests": 12, "below_basic_percentage": 16.7, "below_basic": 2.0, "basic_percentage": 33.3, "basic": 4.0, "proficient_percentage": 25.0, "proficient": 3.0, "advanced_percentage": 25.0, "percentage": 3.0}, "black": {"valid_tests": null, "below_basic_percentage": null, "below_basic": null, "basic_percentage": null, "basic": null, "proficient_percentage": null, "proficient": null, "advanced_percentage": null, "percentage": null}, "asian": {"valid_tests": null, "below_basic_percentage": null, "below_basic": null, "basic_percentage": null, "basic": null, "proficient_percentage": null, "proficient": null, "advanced_percentage": null, "percentage": null}, "native_american": {"valid_tests": null, "below_basic_percentage": null, "below_basic": null, "basic_percentage": null, "basic": null, "proficient_percentage": null, "proficient": null, "advanced_percentage": null, "percentage": null}, "hawaiian_or_pacific_islander": {"valid_tests": null, "below_basic_percentage": null, "below_basic": null, "basic_percentage": null, "basic": null, "proficient_percentage": null, "proficient": null, "advanced_percentage": null, "percentage": null}, "economically_disadvantaged": {"valid_tests": 33, "below_basic_percentage": 6.1, "below_basic": 2.0, "basic_percentage": 24.2, "basic": 8.0, "proficient_percentage": 54.5, "proficient": 18.0, "advanced_percentage": 15.2, "percentage": 5.0}, "students_with_disabilities": {"valid_tests": null, "below_basic_percentage": null, "below_basic": null, "basic_percentage": null, "basic": null, "proficient_percentage": null, "proficient": null, "advanced_percentage": null, "percentage": null}, "english_language_learners": {"valid_tests": null, "below_basic_percentage": null, "below_basic": null, "basic_percentage": null, "basic": null, "proficient_percentage": null, "proficient": null, "advanced_percentage": null, "percentage": null}, "english_language_learners_with_t1_t2": {"valid_tests": 10, "below_basic_percentage": 20.0, "below_basic": 2.0, "basic_percentage": 40.0, "basic": 4.0, "proficient_percentage": 20.0, "proficient": 2.0, "advanced_percentage": 20.0, "percentage": 2.0}, "black_hispanic_native_american": {"valid_tests": 15, "below_basic_percentage": 13.3, "below_basic": 2.0, "basic_percentage": 26.7, "basic": 4.0, "proficient_percentage": 33.3, "proficient": 5.0, "advanced_percentage": 26.7, "percentage": 4.0}}, "5": {"all": {"valid_tests": 38, "below_basic_percentage": 15.7, "below_basic": 6.0, "basic_percentage": 15.8, "basic": 6.0, "proficient_percentage": 55.3, "proficient": 21.0, "advanced_percentage": 13.2, "percentage": 5.0}, "white": {"valid_tests": 24, "below_basic_percentage": 12.4, "below_basic": 3.0, "basic_percentage": 16.7, "basic": 4.0, "proficient_percentage": 54.2, "proficient": 13.0, "advanced_percentage": 16.7, "percentage": 4.0}, "hispanic": {"valid_tests": 12, "below_basic_percentage": 16.7, "below_basic": 2.0, "basic_percentage": 16.7, "basic": 2.0, "proficient_percentage": 58.3, "proficient": 7.0, "advanced_percentage": 8.3, "percentage": 1.0}, "black": {"valid_tests": null, "below_basic_percentage": null, "below_basic": null, "basic_percentage": null, "basic": null, "proficient_percentage": null, "proficient": null, "advanced_percentage": null, "percentage": null}, "asian": {"valid_tests": null, "below_basic_percentage": null, "below_basic": null, "basic_percentage": null, "basic": null, "proficient_percentage": null, "proficient": null, "advanced_percentage": null, "percentage": null}, "native_american": {"valid_tests": null, "below_basic_percentage": null, "below_basic": null, "basic_percentage": null, "basic": null, "proficient_percentage": null, "proficient": null, "advanced_percentage": null, "percentage": null}, "hawaiian_or_pacific_islander": {"valid_tests": null, "below_basic_percentage": null, "below_basic": null, "basic_percentage": null, "basic": null, "proficient_percentage": null, "proficient": null, "advanced_percentage": null, "percentage": null}, "economically_disadvantaged": {"valid_tests": 29, "below_basic_percentage": 13.8, "below_basic": 4.0, "basic_percentage": 20.7, "basic": 6.0, "proficient_percentage": 55.2, "proficient": 16.0, "advanced_percentage": 10.3, "percentage": 3.0}, "students_with_disabilities": {"valid_tests": null, "below_basic_percentage": null, "below_basic": null, "basic_percentage": null, "basic": null, "proficient_percentage": null, "proficient": null, "advanced_percentage": null, "percentage": null}, "english_language_learners": {"valid_tests": null, "below_basic_percentage": null, "below_basic": null, "basic_percentage": null, "basic": null, "proficient_percentage": null, "proficient": null, "advanced_percentage": null, "percentage": null}, "english_language_learners_with_t1_t2": {"valid_tests": null, "below_basic_percentage": null, "below_basic": null, "basic_percentage": null, "basic": null, "proficient_percentage": null, "proficient": null, "advanced_percentage": null, "percentage": null}, "black_hispanic_native_american": {"valid_tests": 13, "below_basic_percentage": 15.4, "below_basic": 2.0, "basic_percentage": 15.4, "basic": 2.0, "proficient_percentage": 61.5, "proficient": 8.0, "advanced_percentage": 7.7, "percentage": 1.0}}}, "social studies": {"all": {"all": {"valid_tests": 127, "below_basic_percentage": null, "below_basic": null, "basic_percentage": null, "basic": null, "proficient_percentage": null, "proficient": null, "advanced_percentage": null, "percentage": null}, "white": {"valid_tests": 85, "below_basic_percentage": null, "below_basic": null, "basic_percentage": null, "basic": null, "proficient_percentage": null, "proficient": null, "advanced_percentage": null, "percentage": null}, "hispanic": {"valid_tests": 34, "below_basic_percentage": 0.0, "below_basic": 0.0, "basic_percentage": 8.8, "basic": 3.0, "proficient_percentage": 41.2, "proficient": 14.0, "advanced_percentage": 50.0, "percentage": 17.0}, "black": {"valid_tests": null, "below_basic_percentage": null, "below_basic": null, "basic_percentage": null, "basic": null, "proficient_percentage": null, "proficient": null, "advanced_percentage": null, "percentage": null}, "asian": {"valid_tests": null, "below_basic_percentage": null, "below_basic": null, "basic_percentage": null, "basic": null, "proficient_percentage": null, "proficient": null, "advanced_percentage": null, "percentage": null}, "native_american": {"valid_tests": null, "below_basic_percentage": null, "below_basic": null, "basic_percentage": null, "basic": null, "proficient_percentage": null, "proficient": null, "advanced_percentage": null, "percentage": null}, "hawaiian_or_pacific_islander": {"valid_tests": null, "below_basic_percentage": null, "below_basic": null, "basic_percentage": null, "basic": null, "proficient_percentage": null, "proficient": null, "advanced_percentage": null, "percentage": null}, "economically_disadvantaged": {"valid_tests": 86, "below_basic_percentage": 0.0, "below_basic": 0.0, "basic_percentage": 5.8, "basic": 5.0, "proficient_percentage": 44.2, "proficient": 38.0, "advanced_percentage": 50.0, "percentage": 43.0}, "students_with_disabilities": {"valid_tests": 11, "below_basic_percentage": 0.0, "below_basic": 0.0, "basic_percentage": 9.1, "basic": 1.0, "proficient_percentage": 36.4, "proficient": 4.0, "advanced_percentage": 54.5, "percentage": 6.0}, "english_language_learners": {"valid_tests": 12, "below_basic_percentage": 0.0, "below_basic": 0.0, "basic_percentage": 16.7, "basic": 2.0, "proficient_percentage": 83.3, "proficient": 10.0, "advanced_percentage": 0.0, "percentage": 0.0}, "english_language_learners_with_t1_t2": {"valid_tests": 23, "below_basic_percentage": 0.1, "below_basic": 0.0, "basic_percentage": 13.0, "basic": 3.0, "proficient_percentage": 56.5, "proficient": 13.0, "advanced_percentage": 30.4, "percentage": 7.0}, "black_hispanic_native_american": {"valid_tests": 40, "below_basic_percentage": 0.0, "below_basic": 0.0, "basic_percentage": 7.5, "basic": 3.0, "proficient_percentage": 40.0, "proficient": 16.0, "advanced_percentage": 52.5, "percentage": 21.0}}, "3": {"all": {"valid_tests": 49, "below_basic_percentage": null, "below_basic": null, "basic_percentage": null, "basic": null, "proficient_percentage": null, "proficient": null, "advanced_percentage": null, "percentage": null}, "white": {"valid_tests": 36, "below_basic_percentage": null, "below_basic": null, "basic_percentage": null, "basic": null, "proficient_percentage": null, "proficient": null, "advanced_percentage": null, "percentage": null}, "hispanic": {"valid_tests": 11, "below_basic_percentage": null, "below_basic": null, "basic_percentage": null, "basic": null, "proficient_percentage": null, "proficient": null, "advanced_percentage": null, "percentage": null}, "black": {"valid_tests": null, "below_basic_percentage": null, "below_basic": null, "basic_percentage": null, "basic": null, "proficient_percentage": null, "proficient": null, "advanced_percentage": null, "percentage": null}, "asian": {"valid_tests": null, "below_basic_percentage": null, "below_basic": null, "basic_percentage": null, "basic": null, "proficient_percentage": null, "proficient": null, "advanced_percentage": null, "percentage": null}, "native_american": {"valid_tests": null, "below_basic_percentage": null, "below_basic": null, "basic_percentage": null, "basic": null, "proficient_percentage": null, "proficient": null, "advanced_percentage": null, "percentage": null}, "hawaiian_or_pacific_islander": {"valid_tests": null, "below_basic_percentage": null, "below_basic": null, "basic_percentage": null, "basic": null, "proficient_percentage": null, "proficient": null, "advanced_percentage": null, "percentage": null}, "economically_disadvantaged": {"valid_tests": 27, "below_basic_percentage": null, "below_basic": null, "basic_percentage": null, "basic": null, "proficient_percentage": null, "proficient": null, "advanced_percentage": null, "percentage": null}, "students_with_disabilities": {"valid_tests": null, "below_basic_percentage": null, "below_basic": null, "basic_percentage": null, "basic": null, "proficient_percentage": null, "proficient": null, "advanced_percentage": null, "percentage": null}, "english_language_learners": {"valid_tests": null, "below_basic_percentage": null, "below_basic": null, "basic_percentage": null, "basic": null, "proficient_percentage": null, "proficient": null, "advanced_percentage": null, "percentage": null}, "english_language_learners_with_t1_t2": {"valid_tests": null, "below_basic_percentage": null, "below_basic": null, "basic_percentage": null, "basic": null, "proficient_percentage": null, "proficient": null, "advanced_percentage": null, "percentage": null}, "black_hispanic_native_american": {"valid_tests": 13, "below_basic_percentage": null, "below_basic": null, "basic_percentage": null, "basic": null, "proficient_percentage": null, "proficient": null, "advanced_percentage": null, "percentage": null}}, "4": {"all": {"valid_tests": 41, "below_basic_percentage": 0.0, "below_basic": 0.0, "basic_percentage": 12.2, "basic": 5.0, "proficient_percentage": 41.5, "proficient": 17.0, "advanced_percentage": 46.3, "percentage": 19.0}, "white": {"valid_tests": 26, "below_basic_percentage": 0.0, "below_basic": 0.0, "basic_percentage": 7.6, "basic": 2.0, "proficient_percentage": 46.2, "proficient": 12.0, "advanced_percentage": 46.2, "percentage": 12.0}, "hispanic": {"valid_tests": 11, "below_basic_percentage": 0.0, "below_basic": 0.0, "basic_percentage": 27.2, "basic": 3.0, "proficient_percentage": 45.5, "proficient": 5.0, "advanced_percentage": 27.3, "percentage": 3.0}, "black": {"valid_tests": null, "below_basic_percentage": null, "below_basic": null, "basic_percentage": null, "basic": null, "proficient_percentage": null, "proficient": null, "advanced_percentage": null, "percentage": null}, "asian": {"valid_tests": null, "below_basic_percentage": null, "below_basic": null, "basic_percentage": null, "basic": null, "proficient_percentage": null, "proficient": null, "advanced_percentage": null, "percentage": null}, "native_american": {"valid_tests": null, "below_basic_percentage": null, "below_basic": null, "basic_percentage": null, "basic": null, "proficient_percentage": null, "proficient": null, "advanced_percentage": null, "percentage": null}, "hawaiian_or_pacific_islander": {"valid_tests": null, "below_basic_percentage": null, "below_basic": null, "basic_percentage": null, "basic": null, "proficient_percentage": null, "proficient": null, "advanced_percentage": null, "percentage": null}, "economically_disadvantaged": {"valid_tests": 31, "below_basic_percentage": 0.0, "below_basic": 0.0, "basic_percentage": 16.1, "basic": 5.0, "proficient_percentage": 48.4, "proficient": 15.0, "advanced_percentage": 35.5, "percentage": 11.0}, "students_with_disabilities": {"valid_tests": null, "below_basic_percentage": null, "below_basic": null, "basic_percentage": null, "basic": null, "proficient_percentage": null, "proficient": null, "advanced_percentage": null, "percentage": null}, "english_language_learners": {"valid_tests": null, "below_basic_percentage": null, "below_basic": null, "basic_percentage": null, "basic": null, "proficient_percentage": null, "proficient": null, "advanced_percentage": null, "percentage": null}, "english_language_learners_with_t1_t2": {"valid_tests": null, "below_basic_percentage": null, "below_basic": null, "basic_percentage": null, "basic": null, "proficient_percentage": null, "proficient": null, "advanced_percentage": null, "percentage": null}, "black_hispanic_native_american": {"valid_tests": 14, "below_basic_percentage": 0.0, "below_basic": 0.0, "basic_percentage": 21.4, "basic": 3.0, "proficient_percentage": 35.7, "proficient": 5.0, "advanced_percentage": 42.9, "percentage": 6.0}}, "5": {"all": {"valid_tests": 37, "below_basic_percentage": null, "below_basic": null, "basic_percentage": null, "basic": null, "proficient_percentage": null, "proficient": null, "advanced_percentage": null, "percentage": null}, "white": {"valid_tests": 23, "below_basic_percentage": null, "below_basic": null, "basic_percentage": null, "basic": null, "proficient_percentage": null, "proficient": null, "advanced_percentage": null, "percentage": null}, "hispanic": {"valid_tests": 12, "below_basic_percentage": null, "below_basic": null, "basic_percentage": null, "basic": null, "proficient_percentage": null, "proficient": null, "advanced_percentage": null, "percentage": null}, "black": {"valid_tests": null, "below_basic_percentage": null, "below_basic": null, "basic_percentage": null, "basic": null, "proficient_percentage": null, "proficient": null, "advanced_percentage": null, "percentage": null}, "asian": {"valid_tests": null, "below_basic_percentage": null, "below_basic": null, "basic_percentage": null, "basic": null, "proficient_percentage": null, "proficient": null, "advanced_percentage": null, "percentage": null}, "native_american": {"valid_tests": null, "below_basic_percentage": null, "below_basic": null, "basic_percentage": null, "basic": null, "proficient_percentage": null, "proficient": null, "advanced_percentage": null, "percentage": null}, "hawaiian_or_pacific_islander": {"valid_tests": null, "below_basic_percentage": null, "below_basic": null, "basic_percentage": null, "basic": null, "proficient_percentage": null, "proficient": null, "advanced_percentage": null, "percentage": null}, "economically_disadvantaged": {"valid_tests": 28, "below_basic_percentage": null, "below_basic": null, "basic_percentage": null, "basic": null, "proficient_percentage": null, "proficient": null, "advanced_percentage": null, "percentage": null}, "students_with_disabilities": {"valid_tests": null, "below_basic_percentage": null, "below_basic": null, "basic_percentage": null, "basic": null, "proficient_percentage": null, "proficient": null, "advanced_percentage": null, "percentage": null}, "english_language_learners": {"valid_tests": null, "below_basic_percentage": null, "below_basic": null, "basic_percentage": null, "basic": null, "proficient_percentage": null, "proficient": null, "advanced_percentage": null, "percentage": null}, "english_language_learners_with_t1_t2": {"valid_tests": null, "below_basic_percentage": null, "below_basic": null, "basic_percentage": null, "basic": null, "proficient_percentage": null, "proficient": null, "advanced_percentage": null, "percentage": null}, "black_hispanic_native_american": {"valid_tests": 13, "below_basic_percentage": null, "below_basic": null, "basic_percentage": null, "basic": null, "proficient_percentage": null, "proficient": null, "advanced_percentage": null, "percentage": null}}}}, "achievements": {"math": {"3_year_average": 63, "grade": "A", "trend": "NC"}, "reading": {"3_year_average": 58, "grade": "A", "trend": "NC"}, "social_studies": {"3_year_average": 61, "grade": "A", "trend": "NC"}, "science": {"3_year_average": 59, "grade": "A", "trend": "NC"}}, "act": {"3_year": {"composite": null, "english": null, "reading": null, "math": null, "science": null}, "1_year": {"composite": null, "english": null, "reading": null, "math": null, "science": null}}, "promotion_rate": {"k_8": 100.0}, "attendance_rate": {"k_8": 95.4, "overall": null}, "dropout_rate": {"cohort": null, "event": null}, "graduation_rate": {"all": null, "nclb_percentage": null, "white": null, "african_american": null, "hispancic": null, "asian": null, "native_american": null, "male": null, "female": null, "economically_disadvantaged": null, "students_with_disabilities": null, "limited_english_proficient": null}}