{"lea_id": "900", "lea_nces_id": "4704380", "nces_id": "470438001753", "id": "25", "name": "Boones Creek Elementary", "type": 1, "url": "http://www.wcde.org/education/school/school.php?sectionid=9&", "phone": "4232833500", "mailing_address": {"street_address": "348 Boones Cr Christian Chr RD", "extended_address": "", "locality": "Gray", "region": "TN", "postal_code": "37615"}, "physical_address": {"street_address": "348 Boones Cr Christian Chr RD", "extended_address": "", "locality": "Gray", "region": "TN", "postal_code": "37615"}, "is_charter": false, "grades_served": ["K", "4"], "safe_school": true, "membership": {"average_daily": 464, "total": 490, "white": {"total": 450, "male": 224, "female": 223}, "african_american": {"total": 17, "male": null, "female": null}, "hispancic": {"total": 21, "male": null, "female": null}, "asian": {"total": null, "male": null, "female": null}, "native_american": {"total": null, "male": null, "female": null}, "limited_english_proficient": null, "exempt_from_reading_assessment": null, "students_with_disabilities": 104, "free_lunch_eligible": 266, "reduced_lunch_eligible": 30, "free_reduced_lunch_eligible": 296, "title_i": 464}, "accountability": {"math": {"all": {"all": {"valid_tests": 177, "below_basic_percentage": 11.3, "below_basic": 20.0, "basic_percentage": 30.5, "basic": 54.0, "proficient_percentage": 38.4, "proficient": 68.0, "advanced_percentage": 19.8, "percentage": 35.0}, "white": {"valid_tests": 168, "below_basic_percentage": 11.3, "below_basic": 19.0, "basic_percentage": 29.8, "basic": 50.0, "proficient_percentage": 39.3, "proficient": 66.0, "advanced_percentage": 19.6, "percentage": 33.0}, "hispanic": {"valid_tests": null, "below_basic_percentage": null, "below_basic": null, "basic_percentage": null, "basic": null, "proficient_percentage": null, "proficient": null, "advanced_percentage": null, "percentage": null}, "black": {"valid_tests": null, "below_basic_percentage": null, "below_basic": null, "basic_percentage": null, "basic": null, "proficient_percentage": null, "proficient": null, "advanced_percentage": null, "percentage": null}, "asian": {"valid_tests": null, "below_basic_percentage": null, "below_basic": null, "basic_percentage": null, "basic": null, "proficient_percentage": null, "proficient": null, "advanced_percentage": null, "percentage": null}, "native_american": {"valid_tests": null, "below_basic_percentage": null, "below_basic": null, "basic_percentage": null, "basic": null, "proficient_percentage": null, "proficient": null, "advanced_percentage": null, "percentage": null}, "hawaiian_or_pacific_islander": {"valid_tests": null, "below_basic_percentage": null, "below_basic": null, "basic_percentage": null, "basic": null, "proficient_percentage": null, "proficient": null, "advanced_percentage": null, "percentage": null}, "economically_disadvantaged": {"valid_tests": 114, "below_basic_percentage": 12.3, "below_basic": 14.0, "basic_percentage": 37.7, "basic": 43.0, "proficient_percentage": 36.0, "proficient": 41.0, "advanced_percentage": 14.0, "percentage": 16.0}, "students_with_disabilities": {"valid_tests": 43, "below_basic_percentage": 34.9, "below_basic": 15.0, "basic_percentage": 37.2, "basic": 16.0, "proficient_percentage": 18.6, "proficient": 8.0, "advanced_percentage": 9.3, "percentage": 4.0}, "english_language_learners": {"valid_tests": null, "below_basic_percentage": null, "below_basic": null, "basic_percentage": null, "basic": null, "proficient_percentage": null, "proficient": null, "advanced_percentage": null, "percentage": null}, "english_language_learners_with_t1_t2": {"valid_tests": null, "below_basic_percentage": null, "below_basic": null, "basic_percentage": null, "basic": null, "proficient_percentage": null, "proficient": null, "advanced_percentage": null, "percentage": null}, "black_hispanic_native_american": {"valid_tests": null, "below_basic_percentage": null, "below_basic": null, "basic_percentage": null, "basic": null, "proficient_percentage": null, "proficient": null, "advanced_percentage": null, "percentage": null}}, "3": {"all": {"valid_tests": 90, "below_basic_percentage": 12.2, "below_basic": 11.0, "basic_percentage": 32.2, "basic": 29.0, "proficient_percentage": 38.9, "proficient": 35.0, "advanced_percentage": 16.7, "percentage": 15.0}, "white": {"valid_tests": 84, "below_basic_percentage": 11.9, "below_basic": 10.0, "basic_percentage": 32.1, "basic": 27.0, "proficient_percentage": 40.5, "proficient": 34.0, "advanced_percentage": 15.5, "percentage": 13.0}, "hispanic": {"valid_tests": null, "below_basic_percentage": null, "below_basic": null, "basic_percentage": null, "basic": null, "proficient_percentage": null, "proficient": null, "advanced_percentage": null, "percentage": null}, "black": {"valid_tests": null, "below_basic_percentage": null, "below_basic": null, "basic_percentage": null, "basic": null, "proficient_percentage": null, "proficient": null, "advanced_percentage": null, "percentage": null}, "asian": {"valid_tests": null, "below_basic_percentage": null, "below_basic": null, "basic_percentage": null, "basic": null, "proficient_percentage": null, "proficient": null, "advanced_percentage": null, "percentage": null}, "native_american": {"valid_tests": null, "below_basic_percentage": null, "below_basic": null, "basic_percentage": null, "basic": null, "proficient_percentage": null, "proficient": null, "advanced_percentage": null, "percentage": null}, "hawaiian_or_pacific_islander": {"valid_tests": null, "below_basic_percentage": null, "below_basic": null, "basic_percentage": null, "basic": null, "proficient_percentage": null, "proficient": null, "advanced_percentage": null, "percentage": null}, "economically_disadvantaged": {"valid_tests": 58, "below_basic_percentage": 12.1, "below_basic": 7.0, "basic_percentage": 36.2, "basic": 21.0, "proficient_percentage": 37.9, "proficient": 22.0, "advanced_percentage": 13.8, "percentage": 8.0}, "students_with_disabilities": {"valid_tests": 19, "below_basic_percentage": 31.6, "below_basic": 6.0, "basic_percentage": 26.3, "basic": 5.0, "proficient_percentage": 26.3, "proficient": 5.0, "advanced_percentage": 15.8, "percentage": 3.0}, "english_language_learners": {"valid_tests": null, "below_basic_percentage": null, "below_basic": null, "basic_percentage": null, "basic": null, "proficient_percentage": null, "proficient": null, "advanced_percentage": null, "percentage": null}, "english_language_learners_with_t1_t2": {"valid_tests": null, "below_basic_percentage": null, "below_basic": null, "basic_percentage": null, "basic": null, "proficient_percentage": null, "proficient": null, "advanced_percentage": null, "percentage": null}, "black_hispanic_native_american": {"valid_tests": null, "below_basic_percentage": null, "below_basic": null, "basic_percentage": null, "basic": null, "proficient_percentage": null, "proficient": null, "advanced_percentage": null, "percentage": null}}, "4": {"all": {"valid_tests": 87, "below_basic_percentage": 10.4, "below_basic": 9.0, "basic_percentage": 28.7, "basic": 25.0, "proficient_percentage": 37.9, "proficient": 33.0, "advanced_percentage": 23.0, "percentage": 20.0}, "white": {"valid_tests": 84, "below_basic_percentage": 10.7, "below_basic": 9.0, "basic_percentage": 27.4, "basic": 23.0, "proficient_percentage": 38.1, "proficient": 32.0, "advanced_percentage": 23.8, "percentage": 20.0}, "hispanic": {"valid_tests": null, "below_basic_percentage": null, "below_basic": null, "basic_percentage": null, "basic": null, "proficient_percentage": null, "proficient": null, "advanced_percentage": null, "percentage": null}, "black": {"valid_tests": null, "below_basic_percentage": null, "below_basic": null, "basic_percentage": null, "basic": null, "proficient_percentage": null, "proficient": null, "advanced_percentage": null, "percentage": null}, "asian": {"valid_tests": null, "below_basic_percentage": null, "below_basic": null, "basic_percentage": null, "basic": null, "proficient_percentage": null, "proficient": null, "advanced_percentage": null, "percentage": null}, "native_american": {"valid_tests": null, "below_basic_percentage": null, "below_basic": null, "basic_percentage": null, "basic": null, "proficient_percentage": null, "proficient": null, "advanced_percentage": null, "percentage": null}, "hawaiian_or_pacific_islander": {"valid_tests": null, "below_basic_percentage": null, "below_basic": null, "basic_percentage": null, "basic": null, "proficient_percentage": null, "proficient": null, "advanced_percentage": null, "percentage": null}, "economically_disadvantaged": {"valid_tests": 56, "below_basic_percentage": 12.5, "below_basic": 7.0, "basic_percentage": 39.3, "basic": 22.0, "proficient_percentage": 33.9, "proficient": 19.0, "advanced_percentage": 14.3, "percentage": 8.0}, "students_with_disabilities": {"valid_tests": 24, "below_basic_percentage": 37.5, "below_basic": 9.0, "basic_percentage": 45.8, "basic": 11.0, "proficient_percentage": 12.5, "proficient": 3.0, "advanced_percentage": 4.2, "percentage": 1.0}, "english_language_learners": {"valid_tests": null, "below_basic_percentage": null, "below_basic": null, "basic_percentage": null, "basic": null, "proficient_percentage": null, "proficient": null, "advanced_percentage": null, "percentage": null}, "english_language_learners_with_t1_t2": {"valid_tests": null, "below_basic_percentage": null, "below_basic": null, "basic_percentage": null, "basic": null, "proficient_percentage": null, "proficient": null, "advanced_percentage": null, "percentage": null}, "black_hispanic_native_american": {"valid_tests": null, "below_basic_percentage": null, "below_basic": null, "basic_percentage": null, "basic": null, "proficient_percentage": null, "proficient": null, "advanced_percentage": null, "percentage": null}}}, "rla": {"all": {"all": {"valid_tests": 177, "below_basic_percentage": 11.3, "below_basic": 20.0, "basic_percentage": 36.7, "basic": 65.0, "proficient_percentage": 39.0, "proficient": 69.0, "advanced_percentage": 13.0, "percentage": 23.0}, "white": {"valid_tests": 168, "below_basic_percentage": 11.9, "below_basic": 20.0, "basic_percentage": 36.3, "basic": 61.0, "proficient_percentage": 38.7, "proficient": 65.0, "advanced_percentage": 13.1, "percentage": 22.0}, "hispanic": {"valid_tests": null, "below_basic_percentage": null, "below_basic": null, "basic_percentage": null, "basic": null, "proficient_percentage": null, "proficient": null, "advanced_percentage": null, "percentage": null}, "black": {"valid_tests": null, "below_basic_percentage": null, "below_basic": null, "basic_percentage": null, "basic": null, "proficient_percentage": null, "proficient": null, "advanced_percentage": null, "percentage": null}, "asian": {"valid_tests": null, "below_basic_percentage": null, "below_basic": null, "basic_percentage": null, "basic": null, "proficient_percentage": null, "proficient": null, "advanced_percentage": null, "percentage": null}, "native_american": {"valid_tests": null, "below_basic_percentage": null, "below_basic": null, "basic_percentage": null, "basic": null, "proficient_percentage": null, "proficient": null, "advanced_percentage": null, "percentage": null}, "hawaiian_or_pacific_islander": {"valid_tests": null, "below_basic_percentage": null, "below_basic": null, "basic_percentage": null, "basic": null, "proficient_percentage": null, "proficient": null, "advanced_percentage": null, "percentage": null}, "economically_disadvantaged": {"valid_tests": 114, "below_basic_percentage": 13.1, "below_basic": 15.0, "basic_percentage": 43.9, "basic": 50.0, "proficient_percentage": 34.2, "proficient": 39.0, "advanced_percentage": 8.8, "percentage": 10.0}, "students_with_disabilities": {"valid_tests": 43, "below_basic_percentage": 30.2, "below_basic": 13.0, "basic_percentage": 44.2, "basic": 19.0, "proficient_percentage": 11.6, "proficient": 5.0, "advanced_percentage": 14.0, "percentage": 6.0}, "english_language_learners": {"valid_tests": null, "below_basic_percentage": null, "below_basic": null, "basic_percentage": null, "basic": null, "proficient_percentage": null, "proficient": null, "advanced_percentage": null, "percentage": null}, "english_language_learners_with_t1_t2": {"valid_tests": null, "below_basic_percentage": null, "below_basic": null, "basic_percentage": null, "basic": null, "proficient_percentage": null, "proficient": null, "advanced_percentage": null, "percentage": null}, "black_hispanic_native_american": {"valid_tests": null, "below_basic_percentage": null, "below_basic": null, "basic_percentage": null, "basic": null, "proficient_percentage": null, "proficient": null, "advanced_percentage": null, "percentage": null}}, "3": {"all": {"valid_tests": 90, "below_basic_percentage": 11.1, "below_basic": 10.0, "basic_percentage": 36.7, "basic": 33.0, "proficient_percentage": 40.0, "proficient": 36.0, "advanced_percentage": 12.2, "percentage": 11.0}, "white": {"valid_tests": 84, "below_basic_percentage": 11.9, "below_basic": 10.0, "basic_percentage": 36.9, "basic": 31.0, "proficient_percentage": 39.3, "proficient": 33.0, "advanced_percentage": 11.9, "percentage": 10.0}, "hispanic": {"valid_tests": null, "below_basic_percentage": null, "below_basic": null, "basic_percentage": null, "basic": null, "proficient_percentage": null, "proficient": null, "advanced_percentage": null, "percentage": null}, "black": {"valid_tests": null, "below_basic_percentage": null, "below_basic": null, "basic_percentage": null, "basic": null, "proficient_percentage": null, "proficient": null, "advanced_percentage": null, "percentage": null}, "asian": {"valid_tests": null, "below_basic_percentage": null, "below_basic": null, "basic_percentage": null, "basic": null, "proficient_percentage": null, "proficient": null, "advanced_percentage": null, "percentage": null}, "native_american": {"valid_tests": null, "below_basic_percentage": null, "below_basic": null, "basic_percentage": null, "basic": null, "proficient_percentage": null, "proficient": null, "advanced_percentage": null, "percentage": null}, "hawaiian_or_pacific_islander": {"valid_tests": null, "below_basic_percentage": null, "below_basic": null, "basic_percentage": null, "basic": null, "proficient_percentage": null, "proficient": null, "advanced_percentage": null, "percentage": null}, "economically_disadvantaged": {"valid_tests": 58, "below_basic_percentage": 10.3, "below_basic": 6.0, "basic_percentage": 43.1, "basic": 25.0, "proficient_percentage": 34.5, "proficient": 20.0, "advanced_percentage": 12.1, "percentage": 7.0}, "students_with_disabilities": {"valid_tests": 19, "below_basic_percentage": 21.0, "below_basic": 4.0, "basic_percentage": 42.1, "basic": 8.0, "proficient_percentage": 15.8, "proficient": 3.0, "advanced_percentage": 21.1, "percentage": 4.0}, "english_language_learners": {"valid_tests": null, "below_basic_percentage": null, "below_basic": null, "basic_percentage": null, "basic": null, "proficient_percentage": null, "proficient": null, "advanced_percentage": null, "percentage": null}, "english_language_learners_with_t1_t2": {"valid_tests": null, "below_basic_percentage": null, "below_basic": null, "basic_percentage": null, "basic": null, "proficient_percentage": null, "proficient": null, "advanced_percentage": null, "percentage": null}, "black_hispanic_native_american": {"valid_tests": null, "below_basic_percentage": null, "below_basic": null, "basic_percentage": null, "basic": null, "proficient_percentage": null, "proficient": null, "advanced_percentage": null, "percentage": null}}, "4": {"all": {"valid_tests": 87, "below_basic_percentage": 11.5, "below_basic": 10.0, "basic_percentage": 36.8, "basic": 32.0, "proficient_percentage": 37.9, "proficient": 33.0, "advanced_percentage": 13.8, "percentage": 12.0}, "white": {"valid_tests": 84, "below_basic_percentage": 11.9, "below_basic": 10.0, "basic_percentage": 35.7, "basic": 30.0, "proficient_percentage": 38.1, "proficient": 32.0, "advanced_percentage": 14.3, "percentage": 12.0}, "hispanic": {"valid_tests": null, "below_basic_percentage": null, "below_basic": null, "basic_percentage": null, "basic": null, "proficient_percentage": null, "proficient": null, "advanced_percentage": null, "percentage": null}, "black": {"valid_tests": null, "below_basic_percentage": null, "below_basic": null, "basic_percentage": null, "basic": null, "proficient_percentage": null, "proficient": null, "advanced_percentage": null, "percentage": null}, "asian": {"valid_tests": null, "below_basic_percentage": null, "below_basic": null, "basic_percentage": null, "basic": null, "proficient_percentage": null, "proficient": null, "advanced_percentage": null, "percentage": null}, "native_american": {"valid_tests": null, "below_basic_percentage": null, "below_basic": null, "basic_percentage": null, "basic": null, "proficient_percentage": null, "proficient": null, "advanced_percentage": null, "percentage": null}, "hawaiian_or_pacific_islander": {"valid_tests": null, "below_basic_percentage": null, "below_basic": null, "basic_percentage": null, "basic": null, "proficient_percentage": null, "proficient": null, "advanced_percentage": null, "percentage": null}, "economically_disadvantaged": {"valid_tests": 56, "below_basic_percentage": 16.1, "below_basic": 9.0, "basic_percentage": 44.6, "basic": 25.0, "proficient_percentage": 33.9, "proficient": 19.0, "advanced_percentage": 5.4, "percentage": 3.0}, "students_with_disabilities": {"valid_tests": 24, "below_basic_percentage": 37.6, "below_basic": 9.0, "basic_percentage": 45.8, "basic": 11.0, "proficient_percentage": 8.3, "proficient": 2.0, "advanced_percentage": 8.3, "percentage": 2.0}, "english_language_learners": {"valid_tests": null, "below_basic_percentage": null, "below_basic": null, "basic_percentage": null, "basic": null, "proficient_percentage": null, "proficient": null, "advanced_percentage": null, "percentage": null}, "english_language_learners_with_t1_t2": {"valid_tests": null, "below_basic_percentage": null, "below_basic": null, "basic_percentage": null, "basic": null, "proficient_percentage": null, "proficient": null, "advanced_percentage": null, "percentage": null}, "black_hispanic_native_american": {"valid_tests": null, "below_basic_percentage": null, "below_basic": null, "basic_percentage": null, "basic": null, "proficient_percentage": null, "proficient": null, "advanced_percentage": null, "percentage": null}}}, "science": {"all": {"all": {"valid_tests": 177, "below_basic_percentage": 18.1, "below_basic": 32.0, "basic_percentage": 26.0, "basic": 46.0, "proficient_percentage": 44.6, "proficient": 79.0, "advanced_percentage": 11.3, "percentage": 20.0}, "white": {"valid_tests": 168, "below_basic_percentage": 17.9, "below_basic": 30.0, "basic_percentage": 26.2, "basic": 44.0, "proficient_percentage": 44.0, "proficient": 74.0, "advanced_percentage": 11.9, "percentage": 20.0}, "hispanic": {"valid_tests": null, "below_basic_percentage": null, "below_basic": null, "basic_percentage": null, "basic": null, "proficient_percentage": null, "proficient": null, "advanced_percentage": null, "percentage": null}, "black": {"valid_tests": null, "below_basic_percentage": null, "below_basic": null, "basic_percentage": null, "basic": null, "proficient_percentage": null, "proficient": null, "advanced_percentage": null, "percentage": null}, "asian": {"valid_tests": null, "below_basic_percentage": null, "below_basic": null, "basic_percentage": null, "basic": null, "proficient_percentage": null, "proficient": null, "advanced_percentage": null, "percentage": null}, "native_american": {"valid_tests": null, "below_basic_percentage": null, "below_basic": null, "basic_percentage": null, "basic": null, "proficient_percentage": null, "proficient": null, "advanced_percentage": null, "percentage": null}, "hawaiian_or_pacific_islander": {"valid_tests": null, "below_basic_percentage": null, "below_basic": null, "basic_percentage": null, "basic": null, "proficient_percentage": null, "proficient": null, "advanced_percentage": null, "percentage": null}, "economically_disadvantaged": {"valid_tests": 114, "below_basic_percentage": 23.7, "below_basic": 27.0, "basic_percentage": 29.8, "basic": 34.0, "proficient_percentage": 37.7, "proficient": 43.0, "advanced_percentage": 8.8, "percentage": 10.0}, "students_with_disabilities": {"valid_tests": 43, "below_basic_percentage": 46.5, "below_basic": 20.0, "basic_percentage": 23.3, "basic": 10.0, "proficient_percentage": 20.9, "proficient": 9.0, "advanced_percentage": 9.3, "percentage": 4.0}, "english_language_learners": {"valid_tests": null, "below_basic_percentage": null, "below_basic": null, "basic_percentage": null, "basic": null, "proficient_percentage": null, "proficient": null, "advanced_percentage": null, "percentage": null}, "english_language_learners_with_t1_t2": {"valid_tests": null, "below_basic_percentage": null, "below_basic": null, "basic_percentage": null, "basic": null, "proficient_percentage": null, "proficient": null, "advanced_percentage": null, "percentage": null}, "black_hispanic_native_american": {"valid_tests": null, "below_basic_percentage": null, "below_basic": null, "basic_percentage": null, "basic": null, "proficient_percentage": null, "proficient": null, "advanced_percentage": null, "percentage": null}}, "3": {"all": {"valid_tests": 90, "below_basic_percentage": 17.8, "below_basic": 16.0, "basic_percentage": 18.9, "basic": 17.0, "proficient_percentage": 53.3, "proficient": 48.0, "advanced_percentage": 10.0, "percentage": 9.0}, "white": {"valid_tests": 84, "below_basic_percentage": 17.9, "below_basic": 15.0, "basic_percentage": 20.2, "basic": 17.0, "proficient_percentage": 51.2, "proficient": 43.0, "advanced_percentage": 10.7, "percentage": 9.0}, "hispanic": {"valid_tests": null, "below_basic_percentage": null, "below_basic": null, "basic_percentage": null, "basic": null, "proficient_percentage": null, "proficient": null, "advanced_percentage": null, "percentage": null}, "black": {"valid_tests": null, "below_basic_percentage": null, "below_basic": null, "basic_percentage": null, "basic": null, "proficient_percentage": null, "proficient": null, "advanced_percentage": null, "percentage": null}, "asian": {"valid_tests": null, "below_basic_percentage": null, "below_basic": null, "basic_percentage": null, "basic": null, "proficient_percentage": null, "proficient": null, "advanced_percentage": null, "percentage": null}, "native_american": {"valid_tests": null, "below_basic_percentage": null, "below_basic": null, "basic_percentage": null, "basic": null, "proficient_percentage": null, "proficient": null, "advanced_percentage": null, "percentage": null}, "hawaiian_or_pacific_islander": {"valid_tests": null, "below_basic_percentage": null, "below_basic": null, "basic_percentage": null, "basic": null, "proficient_percentage": null, "proficient": null, "advanced_percentage": null, "percentage": null}, "economically_disadvantaged": {"valid_tests": 58, "below_basic_percentage": 20.7, "below_basic": 12.0, "basic_percentage": 22.4, "basic": 13.0, "proficient_percentage": 50.0, "proficient": 29.0, "advanced_percentage": 6.9, "percentage": 4.0}, "students_with_disabilities": {"valid_tests": 19, "below_basic_percentage": 36.8, "below_basic": 7.0, "basic_percentage": 21.1, "basic": 4.0, "proficient_percentage": 31.6, "proficient": 6.0, "advanced_percentage": 10.5, "percentage": 2.0}, "english_language_learners": {"valid_tests": null, "below_basic_percentage": null, "below_basic": null, "basic_percentage": null, "basic": null, "proficient_percentage": null, "proficient": null, "advanced_percentage": null, "percentage": null}, "english_language_learners_with_t1_t2": {"valid_tests": null, "below_basic_percentage": null, "below_basic": null, "basic_percentage": null, "basic": null, "proficient_percentage": null, "proficient": null, "advanced_percentage": null, "percentage": null}, "black_hispanic_native_american": {"valid_tests": null, "below_basic_percentage": null, "below_basic": null, "basic_percentage": null, "basic": null, "proficient_percentage": null, "proficient": null, "advanced_percentage": null, "percentage": null}}, "4": {"all": {"valid_tests": 87, "below_basic_percentage": 18.5, "below_basic": 16.0, "basic_percentage": 33.3, "basic": 29.0, "proficient_percentage": 35.6, "proficient": 31.0, "advanced_percentage": 12.6, "percentage": 11.0}, "white": {"valid_tests": 84, "below_basic_percentage": 17.9, "below_basic": 15.0, "basic_percentage": 32.1, "basic": 27.0, "proficient_percentage": 36.9, "proficient": 31.0, "advanced_percentage": 13.1, "percentage": 11.0}, "hispanic": {"valid_tests": null, "below_basic_percentage": null, "below_basic": null, "basic_percentage": null, "basic": null, "proficient_percentage": null, "proficient": null, "advanced_percentage": null, "percentage": null}, "black": {"valid_tests": null, "below_basic_percentage": null, "below_basic": null, "basic_percentage": null, "basic": null, "proficient_percentage": null, "proficient": null, "advanced_percentage": null, "percentage": null}, "asian": {"valid_tests": null, "below_basic_percentage": null, "below_basic": null, "basic_percentage": null, "basic": null, "proficient_percentage": null, "proficient": null, "advanced_percentage": null, "percentage": null}, "native_american": {"valid_tests": null, "below_basic_percentage": null, "below_basic": null, "basic_percentage": null, "basic": null, "proficient_percentage": null, "proficient": null, "advanced_percentage": null, "percentage": null}, "hawaiian_or_pacific_islander": {"valid_tests": null, "below_basic_percentage": null, "below_basic": null, "basic_percentage": null, "basic": null, "proficient_percentage": null, "proficient": null, "advanced_percentage": null, "percentage": null}, "economically_disadvantaged": {"valid_tests": 56, "below_basic_percentage": 26.8, "below_basic": 15.0, "basic_percentage": 37.5, "basic": 21.0, "proficient_percentage": 25.0, "proficient": 14.0, "advanced_percentage": 10.7, "percentage": 6.0}, "students_with_disabilities": {"valid_tests": 24, "below_basic_percentage": 54.2, "below_basic": 13.0, "basic_percentage": 25.0, "basic": 6.0, "proficient_percentage": 12.5, "proficient": 3.0, "advanced_percentage": 8.3, "percentage": 2.0}, "english_language_learners": {"valid_tests": null, "below_basic_percentage": null, "below_basic": null, "basic_percentage": null, "basic": null, "proficient_percentage": null, "proficient": null, "advanced_percentage": null, "percentage": null}, "english_language_learners_with_t1_t2": {"valid_tests": null, "below_basic_percentage": null, "below_basic": null, "basic_percentage": null, "basic": null, "proficient_percentage": null, "proficient": null, "advanced_percentage": null, "percentage": null}, "black_hispanic_native_american": {"valid_tests": null, "below_basic_percentage": null, "below_basic": null, "basic_percentage": null, "basic": null, "proficient_percentage": null, "proficient": null, "advanced_percentage": null, "percentage": null}}}, "social studies": {"all": {"all": {"valid_tests": 177, "below_basic_percentage": 0.0, "below_basic": 0.0, "basic_percentage": 15.8, "basic": 28.0, "proficient_percentage": 35.6, "proficient": 63.0, "advanced_percentage": 48.6, "percentage": 86.0}, "white": {"valid_tests": 168, "below_basic_percentage": 0.0, "below_basic": 0.0, "basic_percentage": 15.5, "basic": 26.0, "proficient_percentage": 36.3, "proficient": 61.0, "advanced_percentage": 48.2, "percentage": 81.0}, "hispanic": {"valid_tests": null, "below_basic_percentage": null, "below_basic": null, "basic_percentage": null, "basic": null, "proficient_percentage": null, "proficient": null, "advanced_percentage": null, "percentage": null}, "black": {"valid_tests": null, "below_basic_percentage": null, "below_basic": null, "basic_percentage": null, "basic": null, "proficient_percentage": null, "proficient": null, "advanced_percentage": null, "percentage": null}, "asian": {"valid_tests": null, "below_basic_percentage": null, "below_basic": null, "basic_percentage": null, "basic": null, "proficient_percentage": null, "proficient": null, "advanced_percentage": null, "percentage": null}, "native_american": {"valid_tests": null, "below_basic_percentage": null, "below_basic": null, "basic_percentage": null, "basic": null, "proficient_percentage": null, "proficient": null, "advanced_percentage": null, "percentage": null}, "hawaiian_or_pacific_islander": {"valid_tests": null, "below_basic_percentage": null, "below_basic": null, "basic_percentage": null, "basic": null, "proficient_percentage": null, "proficient": null, "advanced_percentage": null, "percentage": null}, "economically_disadvantaged": {"valid_tests": 114, "below_basic_percentage": 0.0, "below_basic": 0.0, "basic_percentage": 19.3, "basic": 22.0, "proficient_percentage": 45.6, "proficient": 52.0, "advanced_percentage": 35.1, "percentage": 40.0}, "students_with_disabilities": {"valid_tests": 43, "below_basic_percentage": 0.0, "below_basic": 0.0, "basic_percentage": 44.1, "basic": 19.0, "proficient_percentage": 32.6, "proficient": 14.0, "advanced_percentage": 23.3, "percentage": 10.0}, "english_language_learners": {"valid_tests": null, "below_basic_percentage": null, "below_basic": null, "basic_percentage": null, "basic": null, "proficient_percentage": null, "proficient": null, "advanced_percentage": null, "percentage": null}, "english_language_learners_with_t1_t2": {"valid_tests": null, "below_basic_percentage": null, "below_basic": null, "basic_percentage": null, "basic": null, "proficient_percentage": null, "proficient": null, "advanced_percentage": null, "percentage": null}, "black_hispanic_native_american": {"valid_tests": null, "below_basic_percentage": null, "below_basic": null, "basic_percentage": null, "basic": null, "proficient_percentage": null, "proficient": null, "advanced_percentage": null, "percentage": null}}, "3": {"all": {"valid_tests": 90, "below_basic_percentage": 0.0, "below_basic": 0.0, "basic_percentage": 15.5, "basic": 14.0, "proficient_percentage": 35.6, "proficient": 32.0, "advanced_percentage": 48.9, "percentage": 44.0}, "white": {"valid_tests": 84, "below_basic_percentage": 0.0, "below_basic": 0.0, "basic_percentage": 15.5, "basic": 13.0, "proficient_percentage": 36.9, "proficient": 31.0, "advanced_percentage": 47.6, "percentage": 40.0}, "hispanic": {"valid_tests": null, "below_basic_percentage": null, "below_basic": null, "basic_percentage": null, "basic": null, "proficient_percentage": null, "proficient": null, "advanced_percentage": null, "percentage": null}, "black": {"valid_tests": null, "below_basic_percentage": null, "below_basic": null, "basic_percentage": null, "basic": null, "proficient_percentage": null, "proficient": null, "advanced_percentage": null, "percentage": null}, "asian": {"valid_tests": null, "below_basic_percentage": null, "below_basic": null, "basic_percentage": null, "basic": null, "proficient_percentage": null, "proficient": null, "advanced_percentage": null, "percentage": null}, "native_american": {"valid_tests": null, "below_basic_percentage": null, "below_basic": null, "basic_percentage": null, "basic": null, "proficient_percentage": null, "proficient": null, "advanced_percentage": null, "percentage": null}, "hawaiian_or_pacific_islander": {"valid_tests": null, "below_basic_percentage": null, "below_basic": null, "basic_percentage": null, "basic": null, "proficient_percentage": null, "proficient": null, "advanced_percentage": null, "percentage": null}, "economically_disadvantaged": {"valid_tests": 58, "below_basic_percentage": 0.1, "below_basic": 0.0, "basic_percentage": 17.2, "basic": 10.0, "proficient_percentage": 44.8, "proficient": 26.0, "advanced_percentage": 37.9, "percentage": 22.0}, "students_with_disabilities": {"valid_tests": 19, "below_basic_percentage": 0.0, "below_basic": 0.0, "basic_percentage": 36.8, "basic": 7.0, "proficient_percentage": 31.6, "proficient": 6.0, "advanced_percentage": 31.6, "percentage": 6.0}, "english_language_learners": {"valid_tests": null, "below_basic_percentage": null, "below_basic": null, "basic_percentage": null, "basic": null, "proficient_percentage": null, "proficient": null, "advanced_percentage": null, "percentage": null}, "english_language_learners_with_t1_t2": {"valid_tests": null, "below_basic_percentage": null, "below_basic": null, "basic_percentage": null, "basic": null, "proficient_percentage": null, "proficient": null, "advanced_percentage": null, "percentage": null}, "black_hispanic_native_american": {"valid_tests": null, "below_basic_percentage": null, "below_basic": null, "basic_percentage": null, "basic": null, "proficient_percentage": null, "proficient": null, "advanced_percentage": null, "percentage": null}}, "4": {"all": {"valid_tests": 87, "below_basic_percentage": 0.0, "below_basic": 0.0, "basic_percentage": 16.1, "basic": 14.0, "proficient_percentage": 35.6, "proficient": 31.0, "advanced_percentage": 48.3, "percentage": 42.0}, "white": {"valid_tests": 84, "below_basic_percentage": 0.0, "below_basic": 0.0, "basic_percentage": 15.5, "basic": 13.0, "proficient_percentage": 35.7, "proficient": 30.0, "advanced_percentage": 48.8, "percentage": 41.0}, "hispanic": {"valid_tests": null, "below_basic_percentage": null, "below_basic": null, "basic_percentage": null, "basic": null, "proficient_percentage": null, "proficient": null, "advanced_percentage": null, "percentage": null}, "black": {"valid_tests": null, "below_basic_percentage": null, "below_basic": null, "basic_percentage": null, "basic": null, "proficient_percentage": null, "proficient": null, "advanced_percentage": null, "percentage": null}, "asian": {"valid_tests": null, "below_basic_percentage": null, "below_basic": null, "basic_percentage": null, "basic": null, "proficient_percentage": null, "proficient": null, "advanced_percentage": null, "percentage": null}, "native_american": {"valid_tests": null, "below_basic_percentage": null, "below_basic": null, "basic_percentage": null, "basic": null, "proficient_percentage": null, "proficient": null, "advanced_percentage": null, "percentage": null}, "hawaiian_or_pacific_islander": {"valid_tests": null, "below_basic_percentage": null, "below_basic": null, "basic_percentage": null, "basic": null, "proficient_percentage": null, "proficient": null, "advanced_percentage": null, "percentage": null}, "economically_disadvantaged": {"valid_tests": 56, "below_basic_percentage": 0.1, "below_basic": 0.0, "basic_percentage": 21.4, "basic": 12.0, "proficient_percentage": 46.4, "proficient": 26.0, "advanced_percentage": 32.1, "percentage": 18.0}, "students_with_disabilities": {"valid_tests": 24, "below_basic_percentage": 0.0, "below_basic": 0.0, "basic_percentage": 50.0, "basic": 12.0, "proficient_percentage": 33.3, "proficient": 8.0, "advanced_percentage": 16.7, "percentage": 4.0}, "english_language_learners": {"valid_tests": null, "below_basic_percentage": null, "below_basic": null, "basic_percentage": null, "basic": null, "proficient_percentage": null, "proficient": null, "advanced_percentage": null, "percentage": null}, "english_language_learners_with_t1_t2": {"valid_tests": null, "below_basic_percentage": null, "below_basic": null, "basic_percentage": null, "basic": null, "proficient_percentage": null, "proficient": null, "advanced_percentage": null, "percentage": null}, "black_hispanic_native_american": {"valid_tests": null, "below_basic_percentage": null, "below_basic": null, "basic_percentage": null, "basic": null, "proficient_percentage": null, "proficient": null, "advanced_percentage": null, "percentage": null}}}}, "achievements": {"math": {"3_year_average": 57, "grade": "A", "trend": "NC"}, "reading": {"3_year_average": 56, "grade": "A", "trend": "NC"}, "social_studies": {"3_year_average": 60, "grade": "A", "trend": "NC"}, "science": {"3_year_average": 54, "grade": "A", "trend": "NC"}}, "act": {"3_year": {"composite": null, "english": null, "reading": null, "math": null, "science": null}, "1_year": {"composite": null, "english": null, "reading": null, "math": null, "science": null}}, "promotion_rate": {"k_8": 95.0}, "attendance_rate": {"k_8": 94.6, "overall": null}, "dropout_rate": {"cohort": null, "event": null}, "graduation_rate": {"all": null, "nclb_percentage": null, "white": null, "african_american": null, "hispancic": null, "asian": null, "native_american": null, "male": null, "female": null, "economically_disadvantaged": null, "students_with_disabilities": null, "limited_english_proficient": null}}